[{
  "_id": "642384050b79e41987634e20",
  "background": 3,
  "bio": "Lovin it here!",
  "display": "user 3",
  "email": "user3@fake.com",
  "fanaticScore": "Taylor Swift,Young Nudy,Drake,Nickelback,Logic",
  "follows": "Wave,user2,user1,user4,user5,user6,user7,user8,user9,user10",
  "lastSong": "EA - Young Nudy FT 21 Savage",
  "motto": "lets Rock!",
  "password": "pass3",
  "playlists": "[{\"name\":\"Default Playlist\",\"tracks\":[\"1\",\"2\",\"3\",\"4\",\"5\"]},{\"name\":\"Vibes\",\"tracks\":[\"1\",\"3\",\"5\"]}]",
  "points": 450,
  "profile": 2,
  "quizzes": "2,-1,5,3,5,5,-1",
  "triviaRanks": "Rock,Pop,Hip Hop,Dubstep,Jazz",
  "username": "user3"
},{
  "_id": "643cd8da940a876b27f822b3",
  "background": 1,
  "bio": "music >>> anything",
  "display": "user 1",
  "email": "user1@fake.com",
  "fanaticScore": "Taylor Swift,Young Nudy,Drake,Nickelback,Logic",
  "follows": "Wave,user2,user3,user4,user5,user6,user7,user8,user9,user10",
  "lastSong": "Wassup - Logic",
  "motto": "lit af",
  "password": "pass1",
  "playlists": " [\n    {\n        name: 'Playlist #1',\n        tracks: ['1', '2', '3', '4', '5'],\n    },\n    {\n        name: 'Playlist #2',\n        tracks: ['1', '2', '3'],\n    },\n    {\n        name: 'Playlist #3',\n        tracks: ['1', '2', '3', '4'],\n    }\n]",
  "points": 550,
  "profile": 3,
  "quizzes": "-1,-1,4,2,2,2,-1",
  "triviaRanks": "Rock,Pop,Hip Hop,Dubstep,Jazz",
  "username": "user1"
},{
  "_id": "643cd8f8940a876b27f822b4",
  "background": 2,
  "bio": "Drake is overrated",
  "display": "user 2",
  "email": "user2@fake.com",
  "fanaticScore": "Yeat,Young Nudy,Drake,Nickelback,Logic",
  "follows": "Wave,user1,user3,user4,user5,user6,user7,user8,user9,user10",
  "lastSong": "Everyday - Logic",
  "motto": "superstar",
  "password": "pass2",
  "playlists": " [\n    {\n        name: 'Playlist #1',\n        tracks: ['1', '2', '3', '4', '5'],\n    },\n    {\n        name: 'Playlist #2',\n        tracks: ['1', '3', '4'],\n    },\n    {\n        name: 'Playlist #3',\n        tracks: ['1', '2', '4'],\n    }\n]",
  "points": 475,
  "profile": 1,
  "quizzes": "-1,-1,4,1,5,3,-1",
  "triviaRanks": "Rock,Pop,Hip Hop,Dubstep,Jazz",
  "username": "user2"
},{
  "_id": "643cd91a940a876b27f822b5",
  "background": 2,
  "bio": "Yeat is up next",
  "display": "user 4",
  "email": "user4@fake.com",
  "fanaticScore": "Baby Keem,Young Nudy,Drake,Lil Uzi Vert,Logic",
  "follows": "Wave,user1,user3,user2,user5,user6,user7,user8,user9,user10",
  "lastSong": "Nonstop - Drake",
  "motto": "value only",
  "password": "pass4",
  "playlists": " [\n    {\n        name: 'Playlist #1',\n        tracks: ['1', '2', '3', '4', '5'],\n    },\n    {\n        name: 'Playlist #2',\n        tracks: ['1', '2', '3'],\n    }\n]",
  "points": 362,
  "profile": 1,
  "quizzes": "-1,-1,1,5,5,3,-1",
  "triviaRanks": "Rock,Pop,Hip Hop,Dubstep,Jazz",
  "username": "user4"
},{
  "_id": "643cd939940a876b27f822b6",
  "background": 2,
  "bio": "Imagine Dragons is a crazy name for a band LOLOL",
  "display": "user 5",
  "email": "user5@fake.com",
  "fanaticScore": "Playboi Carti,Kankan,Yeat,Autumn,Summrs",
  "follows": "Wave,user1,user3,user2,user4,user6,user7,user8,user9,user10",
  "lastSong": "God's Plan - Drake",
  "motto": "super cool",
  "password": "pass5",
  "playlists": " [\n    {\n        name: 'Playlist #1',\n        tracks: ['1', '5'],\n    }\n]",
  "points": 403,
  "profile": 2,
  "quizzes": "5,5,1,5,5,3,-1",
  "triviaRanks": "Rock,Pop,Hip Hop,Dubstep,Jazz",
  "username": "user5"
},{
  "_id": "643cd95d940a876b27f822b7",
  "background": 2,
  "bio": "Flawless is a top 2 Yeat track, and it's not 2",
  "display": "user 6",
  "email": "user6@fake.com",
  "fanaticScore": "Lil Yachty,Drake,Logic,Russ,Nav",
  "follows": "Wave,user1,user3,user2,user4,user5,user7,user8,user9,user10",
  "lastSong": "Taking Chances - Nav",
  "motto": "talented",
  "password": "pass6",
  "playlists": " [\n    {\n        name: 'Playlist #1',\n        tracks: ['1', '2', '3'],\n    }\n\n]",
  "points": 706,
  "profile": 2,
  "quizzes": "5,2,1,5,2,3,4",
  "triviaRanks": "Rock,Pop,Hip Hop,Dubstep,Jazz",
  "username": "user6"
},{
  "_id": "643cd97b940a876b27f822b8",
  "background": 2,
  "bio": "idk what to put here anymore",
  "display": "user 7",
  "email": "user7@fake.com",
  "fanaticScore": "Lil Yachty,Drake,Logic,Russ,Nav",
  "follows": "Wave,user1,user3,user2,user4,user5,user6,user8,user9,user10",
  "lastSong": "Know Me - Nav",
  "motto": "up next",
  "password": "pass7",
  "playlists": " [\n    {\n        name: 'Playlist #1',\n        tracks: ['1', '2', '3', '4', '5'],\n    },\n    {\n        name: 'Playlist #2',\n        tracks: ['1', '2', '3'],\n    },\n    {\n        name: 'Playlist #3',\n        tracks: ['1', '2', '3', '4'],\n    }\n]",
  "points": 539,
  "profile": 2,
  "quizzes": "5,5,5,5,5,3,4",
  "triviaRanks": "Rock,Pop,Hip Hop,Dubstep,Jazz",
  "username": "user7"
},{
  "_id": "643cd9bb940a876b27f822b9",
  "background": 2,
  "bio": "I AM THE GREATEST",
  "display": "user 8",
  "email": "user8@fake.com",
  "fanaticScore": "Lil Yachty,Drake,Logic,Russ,Nav",
  "follows": "Wave,user1,user3,user2,user4,user5,user6,user7,user9,user10",
  "lastSong": "Bank Account - Baby Keem FT Lil Uzi Vert",
  "motto": "on top",
  "password": "pass8",
  "playlists": " [\n    {\n        name: 'Playlist #1',\n        tracks: ['1', '2', '3', '4', '5'],\n    },\n    {\n        name: 'Playlist #2',\n        tracks: ['1', '2', '3'],\n    }\n]",
  "points": 1054,
  "profile": 2,
  "quizzes": "5,5,5,5,5,3,5",
  "triviaRanks": "Rock,Pop,Hip Hop,Dubstep,Jazz",
  "username": "user8"
},{
  "_id": "643cd9e8940a876b27f822ba",
  "background": 3,
  "bio": "follow me on instagram at [REDACTED]",
  "display": "user 9",
  "email": "user9@fake.com",
  "fanaticScore": "Playboi Carti,Kankan,Yeat,Autumn,Summrs",
  "follows": "Wave,user1,user3,user2,user4,user5,user6,user7,user8,user10",
  "lastSong": "Trademark USA - Baby Keem",
  "motto": "lets play",
  "password": "pass9",
  "playlists": " [\n    {\n        name: 'Playlist #1',\n        tracks: ['1', '2', '3', '4', '5'],\n    },\n    {\n        name: 'Playlist #2',\n        tracks: ['1', '2', '3'],\n    },\n    {\n        name: 'Playlist #3',\n        tracks: ['1', '2', '3', '4'],\n    }\n]",
  "points": 2244,
  "profile": 3,
  "quizzes": "5,5,5,5,5,4,5",
  "triviaRanks": "Rock,Pop,Hip Hop,Dubstep,Jazz",
  "username": "user9"
},{
  "_id": "643cda22940a876b27f822bb",
  "background": 3,
  "bio": "Lil Uzi needs to drop ASAP",
  "display": "user 10",
  "email": "user10@fake.com",
  "fanaticScore": "Yeat,Young Nudy,Drake,Nickelback,Logic",
  "follows": "Wave,user1,user3,user2,user4,user5,user6,user7,user8,user9",
  "lastSong": "Monster - Imagine Dragons",
  "motto": "enjoy ya self",
  "password": "pass10",
  "playlists": " [\n    {\n        name: 'Playlist #1',\n        tracks: ['1', '2', '3', '4', '5'],\n    },\n    {\n        name: 'Playlist #2',\n        tracks: ['1', '2', '3'],\n    },\n    {\n        name: 'Playlist #3',\n        tracks: ['1', '2', '3', '4'],\n    }\n]",
  "points": 123,
  "profile": 3,
  "quizzes": "5,3,5,2,2,4,5",
  "triviaRanks": "Rock,Pop,Hip Hop,Dubstep,Jazz",
  "username": "user10"
},{
  "_id": "643cddaa940a876b27f822bc",
  "background": 3,
  "bio": "You're looking at the official Wave Account!",
  "display": "Wave Official",
  "email": "admin@wave.com",
  "fanaticScore": "Yeat,Young Nudy,Baby Keem,Lil Uzi Vert,Future",
  "follows": "user3,user2,user1,user4,user5,user6,user7,user8,user9,user10",
  "lastSong": "Flawless - Yeat FT Lil Uzi Vert",
  "motto": "WE DA BEST",
  "password": "admin",
  "playlists": " [\n    {\n        name: 'Top Tracks',\n        tracks: ['1', '3', '5'],\n    }\n]",
  "points": 9999,
  "profile": 2,
  "quizzes": "5,5,5,5,5,5,5",
  "triviaRanks": "Rock,Pop,Hip Hop,Dubstep,Jazz",
  "username": "Wave"
},{
  "_id": {
    "$oid": "64402bf8749fa380edc11c4a"
  },
  "username": "coolDude",
  "password": "pass",
  "email": "user21@gmail.com",
  "follows": "Wave",
  "bio": "Hello World!",
  "lastSong": "N/A",
  "quizzes": "-1,-1,-1,-1,-1,-1,-1",
  "background": "1",
  "profile": "-1",
  "playlist": "[{\"name\":\"Default Playlist\",\"tracks\":[\"1\",\"2\",\"3\",\"4\",\"5\"]}]"
}]